LICENSE
MANIFEST.in
README.md
setup.cfg
setup.py
pymeda/__init__.py
pymeda/clustering.py
pymeda/datasets.py
pymeda/meda.py
pymeda/plotters.py
pymeda/report.py
pymeda/wrappers.py
pymeda.egg-info/PKG-INFO
pymeda.egg-info/SOURCES.txt
pymeda.egg-info/dependency_links.txt
pymeda.egg-info/requires.txt
pymeda.egg-info/top_level.txt
pymeda/templates/report.html