Metadata-Version: 1.1
Name: pymeda
Version: 0.1.12
Summary: Matrix Exploratory Data Analysis
Home-page: https://github.com/neurodata-nomads/pymeda
Author: Jaewon Chung
Author-email: j1c@jhu.edu
License: MIT
Keywords: data visualization analysis
Platform: UNKNOWN
Classifier: Development Status :: 4 - Beta
Classifier: Intended Audience :: Science/Research
Classifier: Topic :: Scientific/Engineering :: Visualization
Classifier: License :: OSI Approved :: MIT License
Classifier: Programming Language :: Python :: 3.6
